{
  "2025-12-02": [
    {
      "title": "à¦à¦à¦¾à¦à¦¨à§à¦à¦¿à¦ à¦¸à¦¿à¦à¦¿",
      "description": "à¦¸à¦¿à¦à¦¿ à¦à¦ªà¦¿à¦ : Worksheet,Cost of goods statement"
    },
    {
      "title": "একাউন্টিং সিটি",
      "description": "সিটি টপিক : Worksheet,Cost of goods statement"
    }
  ],
  "2025-12-01": [
    {
      "title": "à¦¬à¦¾à¦à¦²à¦¾ à¦à¦¸à¦¾à¦à¦¨à¦®à§à¦¨à§à¦",
      "description": "à¦à¦¸à¦¾à¦à¦¨à¦®à§à¦¨à§à¦ à¦à¦ªà¦¿à¦ : à¦¤à§à¦®à¦¾à¦° à¦à§à¦¬à¦¨à§à¦° à¦à§à¦·à§à¦¦à§ à¦à¦²à§à¦ª"
    },
    {
      "title": "বাংলা এসাইনমেন্ট",
      "description": "এসাইনমেন্ট টপিক : তোমার জীবনের ক্ষুদে গল্প"
    }
  ],
  "2025-12-03": [
    {
      "title": "Bangla Assignment",
      "description": "cf"
    }
  ]
}